lego/constants.py
lego/lego_types.py
lego/logger.py
lego/models.py
lego/settings.py
lego/db/redis_legacy.py
lego/db/redis/__init__.py
lego/db/redis/redis.py
lego/db/redis/test_redis.py
lego/db/redshift/__init__.py
lego/db/redshift/errors.py
lego/db/redshift/redshift.py
lego/db/vector_db/models.py
lego/db/vector_db/embed/openai_model.py
lego/db/vector_db/embed/sentence_transformer_model.py
lego/db/vector_db/milvus/__init__.py
lego/db/vector_db/milvus/milvus.py
lego/db/vector_db/milvus/sugar_db.py
lego/db/vector_db/milvus/test_milvus.py
lego/donwload/multi_part_transfer.py
lego/legacy/rag/__init__.py
lego/legacy/rag/app.py
lego/legacy/rag/container.py
lego/legacy/rag/container_types.py
lego/legacy/rag/exceptions.py
lego/legacy/rag/mock.py
lego/legacy/rag/models.py
lego/legacy/rag/rag_types.py
lego/legacy/rag/api_routers/__init__.py
lego/legacy/rag/api_routers/ingest.py
lego/legacy/rag/api_routers/misc.py
lego/legacy/rag/api_routers/retrieve.py
lego/legacy/rag/core/__init__.py
lego/legacy/rag/core/ingest.py
lego/legacy/rag/core/ingest_utils.py
lego/legacy/rag/core/retrieve.py
lego/legacy/rag/eval/__init__.py
lego/legacy/rag/eval/constants.py
lego/legacy/rag/eval/exceptions.py
lego/legacy/rag/eval/llama_eval.py
lego/legacy/rag/eval/prompt.py
lego/legacy/rag/eval/tools.py
lego/legacy/rag/eval/utils.py
lego/legacy/rag/eval/custom/base_service.py
lego/legacy/rag/eval/custom/base_unit.py
lego/legacy/rag/eval/custom/rag_eval_service.py
lego/legacy/rag/eval/custom/rag_eval_unit.py
lego/legacy/rag/tests/john_doe1.json
lego/legacy/rag/tests/john_doe2.json
lego/legacy/rag/tests/test_rag.py
lego/legacy/rag/tests/throw_away_collection.py
lego/litellm/settings.py
lego/litellm/utils/__init__.py
lego/litellm/utils/test_utils.py
lego/litellm/utils/utils.py
lego/llm/__init__.py
lego/llm/exceptions.py
lego/llm/mock.py
lego/llm/prompt.py
lego/llm/settings.py
lego/llm/types.py
lego/llm/router/__init__.py
lego/llm/router/async_router.py
lego/llm/router/simple_router.py
lukoshkin_lego-0.0.25.post2.dist-info/METADATA
lukoshkin_lego-0.0.25.post2.dist-info/WHEEL
lukoshkin_lego-0.0.25.post2.dist-info/licenses/LICENSE
lukoshkin_lego-0.0.25.post2.dist-info/RECORD
